schooltools/__init__.py
schooltools/base.py
schooltools/data.py
schooltools/magnet.py
schooltools-1.2.2.dist-info/METADATA
schooltools-1.2.2.dist-info/WHEEL
schooltools-1.2.2.dist-info/top_level.txt
schooltools-1.2.2.dist-info/RECORD
