Metadata-Version: 2.4
Name: schooltools
Version: 1.2.2
Summary: A set of utilities for my school leleleleell
Author: Muerte
Author-email: eduardopantofillas@gmail.com
Classifier: Programming Language :: Python :: 3
Classifier: License :: OSI Approved :: MIT License
Classifier: Operating System :: OS Independent
Requires-Python: >=3.7
Dynamic: author
Dynamic: author-email
Dynamic: classifier
Dynamic: requires-python
Dynamic: summary
